raspycheck/Lib.py
raspycheck/__init__.py
raspycheck/_exec_cmds.py
raspycheck/_get_info.py
raspycheck/raspycheck.py
raspycheck/Lib/Lib.py
raspycheck/Lib/__init__.py
raspycheck/_exec_cmds/__init__.py
raspycheck/_exec_cmds/_exec_cmds.py
raspycheck/_get_info/__init__.py
raspycheck/_get_info/_get_info.py
raspycheck-0.0.2.dist-info/LICENSE.txt
raspycheck-0.0.2.dist-info/METADATA
raspycheck-0.0.2.dist-info/WHEEL
raspycheck-0.0.2.dist-info/top_level.txt
raspycheck-0.0.2.dist-info/RECORD
